checkmates/__init__.py
checkmates/data_checks/__init__.py
checkmates/data_checks/checks/class_imbalance_data_check.py
checkmates/data_checks/checks/data_check.py
checkmates/data_checks/checks/data_checks.py
checkmates/data_checks/checks/datetime_format_data_check.py
checkmates/data_checks/checks/id_columns_data_check.py
checkmates/data_checks/checks/invalid_target_data_check.py
checkmates/data_checks/checks/multicollinearity_data_check.py
checkmates/data_checks/checks/no_variance_data_check.py
checkmates/data_checks/checks/null_data_check.py
checkmates/data_checks/checks/outliers_data_check.py
checkmates/data_checks/checks/sparsity_data_check.py
checkmates/data_checks/checks/target_distribution_data_check.py
checkmates/data_checks/checks/target_leakage_data_check.py
checkmates/data_checks/checks/ts_parameters_data_check.py
checkmates/data_checks/checks/ts_splitting_data_check.py
checkmates/data_checks/checks/uniqueness_data_check.py
checkmates/data_checks/datacheck_meta/data_check_action.py
checkmates/data_checks/datacheck_meta/data_check_action_code.py
checkmates/data_checks/datacheck_meta/data_check_action_option.py
checkmates/data_checks/datacheck_meta/data_check_message.py
checkmates/data_checks/datacheck_meta/data_check_message_code.py
checkmates/data_checks/datacheck_meta/data_check_message_type.py
checkmates/data_checks/datacheck_meta/utils.py
checkmates/exceptions/__init__.py
checkmates/exceptions/exceptions.py
checkmates/objectives/__init__.py
checkmates/objectives/binary_classification_objective.py
checkmates/objectives/multiclass_classification_objective.py
checkmates/objectives/objective_base.py
checkmates/objectives/regression_objective.py
checkmates/objectives/standard_metrics.py
checkmates/objectives/utils.py
checkmates/pipelines/__init__.py
checkmates/pipelines/component_base.py
checkmates/pipelines/component_base_meta.py
checkmates/pipelines/components.py
checkmates/pipelines/training_validation_split.py
checkmates/pipelines/transformers.py
CheckMates-0.2.0.dist-info/LICENSE
CheckMates-0.2.0.dist-info/METADATA
CheckMates-0.2.0.dist-info/WHEEL
CheckMates-0.2.0.dist-info/top_level.txt
CheckMates-0.2.0.dist-info/RECORD
